MANIFEST.in
README.txt
setup.cfg
setup.py
diviMon.egg-info/PKG-INFO
diviMon.egg-info/SOURCES.txt
diviMon.egg-info/dependency_links.txt
diviMon.egg-info/entry_points.txt
diviMon.egg-info/paste_deploy_config.ini_tmpl
diviMon.egg-info/paster_plugins.txt
diviMon.egg-info/requires.txt
diviMon.egg-info/top_level.txt
divimon/__init__.py
divimon/websetup.py
divimon/config/__init__.py
divimon/config/environment.py
divimon/config/middleware.py
divimon/config/routing.py
divimon/controllers/__init__.py
divimon/controllers/agent.py
divimon/controllers/area.py
divimon/controllers/budget.py
divimon/controllers/budget_expense.py
divimon/controllers/cheques.py
divimon/controllers/commit.py
divimon/controllers/customer.py
divimon/controllers/delivery_confirm.py
divimon/controllers/delivery_confirm_old.py
divimon/controllers/delivery_receipt.py
divimon/controllers/error.py
divimon/controllers/expense.py
divimon/controllers/index.py
divimon/controllers/inventory.py
divimon/controllers/item.py
divimon/controllers/markup.py
divimon/controllers/purchase_order.py
divimon/controllers/purchase_receipt.py
divimon/controllers/purchase_return.py
divimon/controllers/sale.py
divimon/controllers/sales_order.py
divimon/controllers/stocks_out.py
divimon/controllers/template.py
divimon/controllers/trans_item.py
divimon/controllers/transaction.py
divimon/controllers/admin/__init__.py
divimon/controllers/admin/role.py
divimon/controllers/admin/user.py
divimon/controllers/remote/__init__.py
divimon/controllers/remote/base.py
divimon/controllers/remote/client.py
divimon/controllers/remote/server.py
divimon/controllers/uploads/__init__.py
divimon/controllers/uploads/base.py
divimon/controllers/uploads/delivery_receipt.py
divimon/controllers/uploads/item.py
divimon/lib/__init__.py
divimon/lib/app_globals.py
divimon/lib/base.py
divimon/lib/child.py
divimon/lib/helpers.py
divimon/model/__init__.py
divimon/public/dr_print.css
divimon/public/hh.css
divimon/public/hh_report.css
divimon/public/index.html
divimon/public/smsshell.css
divimon/public/date_chooser/calendar.gif
divimon/public/date_chooser/date-functions.js
divimon/public/date_chooser/datechooser.css
divimon/public/date_chooser/datechooser.js
divimon/public/date_chooser/select-free.css
