Metadata-Version: 1.0
Name: diviMon
Version: 0.3.6dev
Summary: A Point-of-Sales System for wholesale.
Home-page: UNKNOWN
Author: Emanuel Calso and Erwin Pacheco
Author-email: egcalso@gmail.com, erwin.pacheco@gmail.com
License: GPL2
Platform: UNKNOWN
